gh_download/__init__.py
gh_download/cli.py
gh_download/gh.py
gh_download/py.typed
gh_download/rich.py
gh_download-0.5.0.dist-info/licenses/LICENSE
gh_download-0.5.0.dist-info/METADATA
gh_download-0.5.0.dist-info/WHEEL
gh_download-0.5.0.dist-info/entry_points.txt
gh_download-0.5.0.dist-info/top_level.txt
gh_download-0.5.0.dist-info/RECORD
