Metadata-Version: 2.4
Name: gh-download
Version: 0.5.0
Summary: A CLI tool to download files from GitHub repositories, including private ones, by leveraging your existing gh CLI authentication.
Author-email: Bas Nijholt <bas@nijho.lt>
Project-URL: Homepage, https://github.com/basnijholt/gh-download
Requires-Python: >=3.10
License-File: LICENSE
Requires-Dist: requests>=2.32.3
Requires-Dist: rich>=14.0.0
Requires-Dist: typer>=0.12.3
Provides-Extra: test
Requires-Dist: pytest>=7.0.0; extra == "test"
Requires-Dist: pytest-asyncio>=0.20.0; extra == "test"
Requires-Dist: pytest-cov>=4.0.0; extra == "test"
Requires-Dist: requests>=2.25.1; extra == "test"
Provides-Extra: dev
Requires-Dist: gh-download[test]; extra == "dev"
Requires-Dist: pre-commit>=3.0.0; extra == "dev"
Requires-Dist: versioningit; extra == "dev"
Requires-Dist: markdown-code-runner; extra == "dev"
Requires-Dist: ruff; extra == "dev"
Requires-Dist: notebook; extra == "dev"
Dynamic: license-file
